tokenkeeper/__init__.py
tokenkeeper/auth.py
tokenkeeper/db.py
tokenkeeper/main.py
tokenkeeper/models.py
tokenkeeper/probes.py
tokenkeeper/tables.py
tokenkeeper/utils.py
tokenkeeper/data/__init__.py
tokenkeeper/data/tokens.py
tokenkeeper/data/users.py
tokenkeeper_api-0.0.4.dist-info/licenses/LICENSE
tokenkeeper_api-0.0.4.dist-info/METADATA
tokenkeeper_api-0.0.4.dist-info/WHEEL
tokenkeeper_api-0.0.4.dist-info/top_level.txt
tokenkeeper_api-0.0.4.dist-info/RECORD
