Metadata-Version: 2.4
Name: tokenkeeper-api
Version: 0.0.4
Summary: A minimal FastAPI service for creating, verifying, and revoking user-scoped API tokens. Uses Argon2 hashing and PostgreSQL for secure token management.
Requires-Python: >=3.12
License-File: LICENSE
Requires-Dist: pytest==8.*
Requires-Dist: asgi-lifespan
Requires-Dist: fastapi[standard]
Requires-Dist: asyncpg
Requires-Dist: sqlalchemy[asyncio]
Requires-Dist: pydantic
Requires-Dist: passlib[argon2]
Requires-Dist: cognito-jwt-verifier
Dynamic: license-file
